ov_training_kit/__init__.py
ov_training_kit/pytorch/__init__.py
ov_training_kit/pytorch/base_wrapper.py
ov_training_kit/pytorch/classification_wrapper.py
ov_training_kit/pytorch/compiler.py
ov_training_kit/pytorch/detection_wrapper.py
ov_training_kit/pytorch/regression_wrapper.py
ov_training_kit/pytorch/segmentation_wrapper.py
ov_training_kit/sklearn/__init__.py
ov_training_kit/sklearn/classification/__init__.py
ov_training_kit/sklearn/classification/knn.py
ov_training_kit/sklearn/classification/logistic_regression.py
ov_training_kit/sklearn/classification/nusvc.py
ov_training_kit/sklearn/classification/random_forest.py
ov_training_kit/sklearn/classification/svc.py
ov_training_kit/sklearn/clustering/__init__.py
ov_training_kit/sklearn/clustering/dbscan.py
ov_training_kit/sklearn/clustering/kmeans.py
ov_training_kit/sklearn/decomposition/__init__.py
ov_training_kit/sklearn/decomposition/pca.py
ov_training_kit/sklearn/decomposition/tsne.py
ov_training_kit/sklearn/neighbors/__init__.py
ov_training_kit/sklearn/neighbors/nearest_neighbors.py
ov_training_kit/sklearn/regression/__init__.py
ov_training_kit/sklearn/regression/elastic_net.py
ov_training_kit/sklearn/regression/lasso.py
ov_training_kit/sklearn/regression/linear_regression.py
ov_training_kit/sklearn/regression/nusvr.py
ov_training_kit/sklearn/regression/random_forest_regressor.py
ov_training_kit/sklearn/regression/ridge.py
ov_training_kit/sklearn/regression/svr.py
ov_training_kit/tensorflow/__init__.py
ov_training_kit/tensorflow/base_wrapper.py
ov_training_kit/tensorflow/classification_wrapper.py
ov_training_kit/tensorflow/detection_wrapper.py
ov_training_kit/tensorflow/regression_wrapper.py
ov_training_kit/tensorflow/segmentation_wrapper.py
ov_training_kit-0.2.3.dist-info/METADATA
ov_training_kit-0.2.3.dist-info/WHEEL
ov_training_kit-0.2.3.dist-info/top_level.txt
ov_training_kit-0.2.3.dist-info/RECORD
