Metadata-Version: 2.4
Name: ov_training_kit
Version: 0.2.3
Summary: Wrappers for scikit-learn, PyTorch and Tensorflow models with OpenVINO optimization
Home-page: https://github.com/openvinotoolkit/openvino_contrib
License: Apache-2.0
Keywords: openvino scikit-learn pytorch machine-learning edge-ai tensorflow
Classifier: Programming Language :: Python :: 3
Classifier: License :: OSI Approved :: Apache Software License
Classifier: Operating System :: OS Independent
Classifier: Intended Audience :: Developers
Classifier: Intended Audience :: Science/Research
Classifier: Topic :: Scientific/Engineering :: Artificial Intelligence
Requires-Python: >=3.8, <3.12
Requires-Dist: scikit-learn==1.2.2
Requires-Dist: scikit-learn-intelex==2023.1.1
Requires-Dist: torch>=1.12.0
Requires-Dist: openvino>=2023.0
Requires-Dist: nncf>=2.7.0
Requires-Dist: joblib>=1.2.0
Requires-Dist: numpy<2.0.0,>=1.21.0
Requires-Dist: psutil>=5.9.0
Provides-Extra: ipex-cpu
Requires-Dist: intel_extension_for_pytorch>=2.1.0; extra == "ipex-cpu"
Provides-Extra: ipex-xpu
Requires-Dist: torch==2.7.0; extra == "ipex-xpu"
Requires-Dist: torchvision==0.22.0; extra == "ipex-xpu"
Requires-Dist: torchaudio==2.7.0; extra == "ipex-xpu"
Requires-Dist: intel-extension-for-pytorch==2.7.10+xpu; extra == "ipex-xpu"
Provides-Extra: tensorflow
Requires-Dist: tensorflow>=2.12.0; extra == "tensorflow"
Requires-Dist: intel_extension_for_tensorflow>=2.12.0; extra == "tensorflow"
Requires-Dist: tensorflow_model_optimization>=0.7.0; extra == "tensorflow"
Provides-Extra: dev
Requires-Dist: pytest>=7.0.0; extra == "dev"
Requires-Dist: pytest-cov>=4.0.0; extra == "dev"
Requires-Dist: flake8>=6.0.0; extra == "dev"
Requires-Dist: black>=23.0.0; extra == "dev"
Requires-Dist: isort>=5.10.0; extra == "dev"
Provides-Extra: docs
Requires-Dist: sphinx>=5.0.0; extra == "docs"
Requires-Dist: sphinx_rtd_theme>=1.0.0; extra == "docs"
Dynamic: classifier
Dynamic: description
Dynamic: description-content-type
Dynamic: home-page
Dynamic: keywords
Dynamic: license
Dynamic: provides-extra
Dynamic: requires-dist
Dynamic: requires-python
Dynamic: summary
